{"q+DBL6Ip/DUrNNhuYzaAOQ==":"mbr.jpg","gsjYRdHRUVZKKoL5D2DVIg==":"mbr.jpeg","Jvd/Hv+E6dzGxsxf1OSMGw==":"mbr-1.jpg","Rkh6VN1geuklqasa+Hps8w==":"mbr-2.jpg","OgtCKla7ZhzAplY/dXMFRQ==":"mbr-3.jpg","7cAX25vTViPzsEpxKtfgnw==":"mbr-4.jpg","Bzg68IuBcRh9sFO8XLZmEQ==":"mbr-5.jpg","3L8x5ialuZVROWzapuz4nA==":"mbr-6.jpg","5Yxz1Ro3xgEvJK27QZYsvA==":"mbr-1.jpeg","orRrDp0O7uYYPUWXMASTrg==":"mbr-2.jpeg","hNnJ/ah4jJ+gnKLIjKCM+Q==":"mbr-3.jpeg","8lvp9ISHPOav0iH8GHzE5A==":"mbr-596x397.jpg","4WRGugLLJp1qA5Gcg3svcQ==":"fond%20%C3%A9cran%20widows%2011-1900x1188.jpg","o7HIsD4rzTbAdtn5vtcHlQ==":"icone%201-257x196.jpg","JVYEIyqx9DKTP2xnkfQTDQ==":"illustration%20de%20visuel%20design%20graphique%20en%20350_360px%20coherent%20,%20simple%20et%20realiste,-2000x2000.jpeg","lUKXKXfahirVX4HZ2B7sOw==":"design%20sans%20titre%20(1)-940x788.png","Ss4SL2rMftGovhKW3NOzaA==":"logo%20pp-96x96.png","1JW1azL7Hy9OLGxP+aYa2w==":"2151933139-1076x736.jpg","HQALFCDf11DdjgVndwi2zg==":"web%20img1-1000x560.png","Vp36+FPcKL/xaMWZdqtyUg==":"1753578086223-600x600.jpg","ATXwHhBpszfY8LMHDutyTQ==":"elt%20graph-1900x1900.jpg","ixQIv7duliXG1ziB3/PNeA==":"img-20240725-wa0019-740x493.jpg","+lmZuIPbIOeYR9R8GAdSsw==":"img-20240725-wa0022-626x626.jpg","TqOs5tzJkS72KYybjWTsng==":"elt%20graph-2084x2084.jpg","7P9+g+zfGXW4FFUmFHEYPQ==":"icone%203-275x183.jpg","RJnOF1BUtNPfZGww9yvCYQ==":"dribbble-400x400.png","U+4/5rytEFE8uQIqEMlaXQ==":"freepik_logo_png_(2)-400x400.png","YGAw5pPxFk6pSmvzxQ7M2Q==":"gemini_generated_image_nhjjtcnhjjtcnhjj-400x400.png","TaOnd/kVtayysM37IT1glg==":"idfqnuznmf_logos-400x400.jpg","GJlsNPf33y52ulx4fe4rCg==":"canva-225x225.jpg","d5wmKM04mNd3SHA+/q9ckg==":"img-20240725-wa0019-561x374.jpg","9P84uw4vIZhR6WSeWZIBUw==":"132620-770x697.jpg","ot7pr9PZWwpS1sr8vlG2UQ==":"7333606-3540111-770x369.jpg","n7yB/THHgzdb1wNxyZOPBg==":"124155-770x433.jpg","w8Y9E5v+OcgB/65HVFUENw==":"charte-263x191.jpg","peenMeQQvoH14oKKcJUTkA==":"gemini_generated_image_9war639war639war-770x558.png","flvt+yTlwkjYBPbvF+HJbQ==":"actu1.webp","jK2Y7Q4+7NobR+4u9yiK6A==":"actu%202-1076x605.jpg","ZI1KP4MkKM7vfaCS46406g==":"actu%203.webp","CmMtUydkr9/PxzqAvE1Vgg==":"actu%204.webp","ojER1Y2tHj36Oq9SQkQLtA==":"2149121640-1022x1500.jpg","3wCTDX47GF2O92nXwaqE+A==":"img_20240731_093041-500-1872x4160.jpg","vyOI2f7JF5DVFSJD5Nyh9g==":"img_20240731_093041-500-1872x4160.jpeg","/qr2Aw6XG1pItlLkKPJxFw==":"132620-1500x1358.jpg","2Nf+HBJLKDxmYZQK3CPudQ==":"graphic-designer-business-card-design-graphic-design-308e926815204c7a1cbf44d12c7b4b07-759x506.png","Wk75LZpcUA6IhHski3coUw==":"gemini_generated_image_opai8bopai8bopai-759x505.png","eYW2UoE2uFi1gomVafNPNQ==":"ai-165x148.png","cRQZCoi2PzWngDTQ8bv4HQ==":"psd-185x148.png","RUCLwLCJqE4+Wbi3UZY1XA==":"pr-151x148.png","tr3yzxOL5J/tMoeetisLEA==":"ae-152x148.png","9S4Kjf1xf0tI/9DR3FNfJQ==":"ma-225x225.png","TJKmXhz6w6y64Qpc+D/OfA==":"cx-225x225.png"}